{
  "created_at": "2026-03-29T16:00:13.820780",
  "total_items": 5,
  "items": [
    {
      "id": "1774769457490_三水昊通光伏组件拆装承包合同 - 盖章.pdf",
      "filename": "三水昊通光伏组件拆装承包合同 - 盖章.pdf",
      "project_id": "1774769457490",
      "content": "",
      "file_path": "\\uploads\\1774769457490\\三水昊通光伏组件拆装承包合同 - 盖章.pdf",
      "created_at": "2026-03-29T16:00:13.820780",
      "updated_at": "2026-03-29T16:00:13.820780"
    },
    {
      "id": "1774769457490_昊通分布式光伏工程总承包合同.pdf",
      "filename": "昊通分布式光伏工程总承包合同.pdf",
      "project_id": "1774769457490",
      "content": "",
      "file_path": "\\uploads\\1774769457490\\昊通分布式光伏工程总承包合同.pdf",
      "created_at": "2026-03-31T10:57:20.955878",
      "updated_at": "2026-03-31T10:57:20.955878"
    },
    {
      "id": "1774859130487_光伏EMC合同-蚬华.pdf",
      "filename": "光伏EMC合同-蚬华.pdf",
      "project_id": "1774859130487",
      "content": "",
      "file_path": "\\uploads\\1774859130487\\光伏EMC合同-蚬华.pdf",
      "created_at": "2026-03-31T10:57:56.126050",
      "updated_at": "2026-03-31T10:57:56.126050"
    },
    {
      "id": "1774859130487_顺德蚬华多媒体制品有限公司3.132MWh储能项目方案建议书20250228.pdf",
      "filename": "顺德蚬华多媒体制品有限公司3.132MWh储能项目方案建议书20250228.pdf",
      "project_id": "1774859130487",
      "content": "佛山市顺德区蚬华多媒体制品有限公司\n1.5MW/3.132MWh储能项目建议书\n英备特电气科技有限公司\n2025年2月储能解决方案建议书\n目录\n1.佛山市顺德区蚬华多媒体制品有限公司储能项目................................3\n1.1.项目背景...........................................................3\n1.2.电价情况...........................................................3\n1.3.储能系统充放策略及容量配置.........................................5\n1.3.1.储能系统充放策略...............................................5\n1.3.2.储能容量配置...................................................5\n1.4.储能系统整体方案...................................................8\n1.4.1.储能系统接入方案...............................................8\n1.4.2.储能布置........................................................8\n2.项目合作模式及收益测算....................................................9\n2.1.一体化解决方案及收益测算...........................................9\n3.公司介绍.................................................................10\n4.工商业储能项目情况背景分析...............................................13\n4.1.工商业储能项目背景................................................13\n4.2.建设绿色工厂......................................................14\n4.3.降低运营成本......................................................14\n4.4.顺应电力市场改革..................................................14\n5.储能系统技术介绍.........................................................15\n5.1.第一代储能系统集成技术............................................15\n5.2.第二代储能系统集成技术............................................15\n5.3.第三代柔性储能系统集成技术........................................16\n6.储能系统产品类型.........................................................18\n6.1.机柜式储能系统....................................................18\n6.2.集装箱式储能系统..................................................19\n7.储能项目案例展示.........................................................20\n7.1.日丰企业(佛山)有限公司柔性储能项目.................................20\n7.2.英备特电气科技有限公司储能项目....................................21\n7.3.东莞龙鑫运动用品有限公司储能项目..................................21\n7.4.浙江东睦科达磁电科技有限公司储能项目..............................22\n7.5.聚灿光电科技(宿迁)有限公司用户侧储能项目...........................22\n7.6.湖南宏旺新材料科技有限公司电化学储能项目..........................2331.佛山市顺德区蚬华多媒体制品有限公司储能项目\n1.1.项目背景\n佛山市顺德区蚬华多媒体制品有限公司成立于1995-06-12，法定代表人为翁国基，注册\n资本为650万美元，统一社会信用代码为914406066176568785，企业注册地址位于佛山市\n顺德区北滘镇北滘工业园三乐东路18号，所属行业为电气机械和器材制造业。佛山市顺德\n区蚬华多媒体制品有限公司目前的经营状态为在营（开业）企业。\n图1-1公司资信\n1.2.电价情况\n统计南网广东省佛山市电力有限公司代理购电大工业1-10千伏用户2024年全年电价表如\n下所示：\n表1-12024年用户电价表\n电度用电价格 1-10千伏\n(单位：元/干瓦时)\n尖峰 高峰 平时 低谷\n2024年12月 1.459869 1.1732690.7015690.283869\n2024年11月 1.435169 1.1535690.6899690.279269\n2024年10月 1.461069 1.1743690.7021690.283969\n2024年9月 1.453469 1.1682690.6985690.282669\n2024年8月 1.450669 1.1659690.6972690.28216942024年7月 1.416869 1.1388690.6813690.276169\n2024年6月 1.566669 1.1339690.6784690.275069\n2024年5月 1.476669 1.1867690.7094690.286669\n2024年4月 1.476369 1.1865690.7093690.286669\n2024年3月 1.542269 1.1863690.7092690.286669\n2024年2月 1.500769 1.2060690.7207690.291169\n2024年1月 1.461169 1.1743690.7021690.283969\n表1-22024年年均代理购电价格表\n用电分类代理购电用户分时电价\n（元/千瓦时）\n大工业\n用电1-10kV千伏\n（两部制）尖1.475086\n峰1.170702\n平0.700036\n谷0.283194\n根据政策绘制广东省分时电价曲线如下所示：\n图1-2广东电价时段分布\n广东省峰谷时段设置为：\n年度内7、8、9全月执行尖高峰时段，尖峰时段为：11:00-12:00、15:00-17:00。\n高峰时段为：10:00-11:00、14:00-15:00、17:00-19:00。\n其他月份（1-6月、10-12月）高峰段为：10:00-12:00、14:00-19:00。\n平段时间为：8:00-10:00、12:00-14:00、19:00-24:00。\n全年低谷时段为：0:00-8:00。\n根据广东峰谷时段设置，储能系统建议配置为0.5C系统，即2个小时能够完成一次满充5满放，全天有两个电价高峰时段，因此每日可完成两充两放。\n1.3.储能系统充放策略及容量配置\n1.3.1.储能系统充放策略\n根据广东省峰谷分时时段，储能系统在电价谷时充电，尖峰时放电，每日2充2放的运行\n模式。储能充放电策略如下：\n表1-3储能充放电策略（7、8、9月）\n类型 时段 模式 时长/h 说明\n谷 0~8时 充电 8 夜间小功率充满后自动停止\n峰 10~12时 放电 2 储能电池放空后，自动停止\n平 12~14时 充电 2 储能电池充满后自动停止\n尖/峰 15~17时 放电 2 储能电池放空后，自动停止\n表1-4储能充放电策略（1-6、10-12月）\n类型 时段 模式 时长/h 说明\n谷 0~8时 充电 8 夜间小功率充满后自动停止\n峰 10~12时 放电 2 储能电池放空后，自动停止\n平 12~14时 充电 2 储能电池充满后自动停止\n峰 14~19时 放电 5 储能电池放空后，自动停止\n1.3.2.储能容量配置\n项目收资情况：\n电费单\n图1-3企业8月电费单61)项目资料分析：\n分析佛山市顺德区蚬华多媒体制品有限公司2024年8月电费单，可以了解该企业为两\n部制大工业用电，电压等级为10KV，该企业缴费方式为每月按容缴费。\n2)厂区负荷情况：\n分析负荷曲线，园区内负荷普遍持续在800kW~2500kW左右，厂区变压器受电容量为\n7760kVA，有较大空间进行配储。下面是抽取部分月份的负荷曲线：\n图1-42024年12月负荷曲线\n图1-52025年1月负荷曲线7\n图1-62025年2月负荷曲线\n结合广东省分时电价分布、园区负荷时段分布，不难分析，配置任何储能系统要保证该\n系统在电价低谷平期能够有一定的充电空间负荷、在电价高（尖）峰期厂区需要有充足的负\n荷消纳才能实现两充两放，达到最大经济效益：\n①园区谷期0-8时、12-14时负荷较低，储能系统在此时充电空间充足；\n②园区上午10-12时负荷相对较低，负荷曲线整体走向与分时电价曲线吻合，可以进行\n配储；\n③厂区变压器空间充足，主要配储依据为高（尖）峰期消纳电量。\n以下分别计算其电价低谷、高峰、平期、尖峰期负荷数据，统计日充放电量。将数据\n按照分时电价时段记录成下表：\n年月 谷kW可充电\n量kWh高峰kW消纳电\n量kWh平kW可充电\n量kWh变压器\n容量kW\n2024年12月168837072155231041472110247760\n2025年1月164037408144028801288113927760\n2025年2月152038248153230641208115527760\n3)储能配置分析：\n从表中数据可以分析，每个月的配储依据会有所不同，整体还是从上午高峰期消纳电\n量或中午平期可充电量得出配储规模。\n基于储能系统两次充放最大利用率原则，结合两个计量点日充放电量消纳情况，整体\n考虑建议为佛山市顺德区蚬华多媒体制品有限公司配置1.5MW/3.132MWh的储能系统，选\n用12台我司单台规格为261kWh的储能一体机，采用低压接入的技术方案，按组串式布置分\n为2个储能单元，每个储能单元由6台储能一体机组成一套750kW/1566kWh的储能系统。全\n系统设定以削峰填谷为主要运行模式每日完成两充两放，储能系统在00:00-08:00时谷段进行\n充电(8小时)，10:00-12:00之间第一个峰段放电(2小时)，12:00-14:00之间将电池充电(2小8时)，15:00-17:00时放电(2小时)，预计每日储能系统总容量充放1.9次。实际配置容量及配置\n接入点要根据施工图设计为准。\n1.4.储能系统整体方案\n1.4.1.储能系统接入方案\n400V母线低压接入储能方案\n本方案采用了英备特研发团队经过多场景应用验证的成熟方案，在厂区400V母线上接\n入储能系统，大大降低接入施工技术难度及建设成本，同时提升储能系统的充放效率，具有\n高能量密度、高可靠性、高安全性、快速响应等优势。方案以秉持科学安全，绿色环保，集\n约用地的原则进行设计，缩减客户建设周期，促进环境友好发展。系统采用可拆卸机柜式式\n模块化设计，易安装、运输、维护和系统扩容。电池系统由能量密度高、成本低、安全无污\n染的磷酸铁锂储能电池以一定的串并联方式进行连接，配以先进的电池管理系统，具有灵活、\n可靠，易扩展升级等特点。\n图1-8400V母线低压接入系统图\n1.4.2.储能布置\n项目共设计为1.5MW/3.132MWh电化学储能系统，按组串式布置，机柜采用磷酸铁锂\n电池。最终接入方案以现场实际情况及当地电网公司审核意见为准。92.项目合作模式及收益测算\n2.1.一体化解决方案及收益测算\n(1)合作模式：投资方投资建设储能系统，节约电费双方分成；\n(2)收益部分说明：\n①储能节约电费：投资方80%：佛山市顺德区蚬华多媒体制品有限公司20%；\n②其他收益：除特殊规定收益归属外，双方按50%：50%分成。\n(3)设备期限：15年\n表2-11.5MW/3.132MWh储能系统EPC收益明细表\n年放电量(万度）年别用电方分享比例投资方 蚬华\n峰谷收益 峰谷收益\n156.02 第1年 80%：20% 73.58 18.39\n149.52 第2年 80%：20% 70.51 17.63\n143.83 第3年 80%：20% 67.83 16.96\n138.96 第4年 80%：20% 65.53 16.38\n134.49 第5年 80%：20% 63.42 15.86\n130.63 第6年 80%：20% 61.60 15.40\n127.07 第7年 80%：20% 59.93 14.98\n124.07 第8年 80%：20% 58.51 14.63\n156.02 第9年 80%：20% 73.58 18.39\n149.52 第10年 80%：20% 70.51 17.63\n143.83 第11年 80%：20% 67.83 16.96\n138.96 第12年 80%：20% 65.53 16.38\n134.49 第13年 80%：20% 63.42 15.86\n130.63 第14年 80%：20% 61.60 15.40\n127.07 第15年 80%：20% 59.93 14.98\n2085.10 15年总计 983.32 245.83\n139.01 15年年均 65.55 16.39\n在EMC合作模式情况下，投资方需投入资金313.2万元参与储能电站的建设，项目投\n运后预计平均每年为贵公司获得电费收益65.55万元，整体项目运营15年内共计收入983.32\n万元，项目测算静态投资回报周期为5.55年，总投资收益率约7.74%。\n用电方佛山市顺德区蚬华多媒体制品有限公司无需投入资金参与储能电站的建设，且\n项目投运后预计平均每年为贵公司节省电费支出16.39万元，整体项目运营15年内共计节省\n支出245.83万元。\n注：以上投资测算均包含储能电站运行15年内所需电站运维费用、电站保险费用，以及\n第8~9年更换一次电池费用。本投资测算仅供参考，实际收益以储能电站实际运行收益为准。103.公司介绍\n英备特电气科技有限公司于2020年9月成立，注册资金3000万元，是行业领先的新能源\n光伏、储能、充电服务商。英备特专注于储能系统产品、新能源汽车充电产品的研发、生产、\n销售和服务，主要产品有储能锂电池系统、新能源汽车充电设备等，并致力于提供光储充全\n生命周期解决方案。\n图3-1英备特总部图\n英备特厂房面积23000平方米，集研发、生产、销售及配套于一体，配备了年产能达\n5GWh的储能PACK全自动生产线及总装生产产线，和年产能6000套的一体式、分体式充电\n桩生产线，同时在深圳和西安设有研发中心，为产品及服务的高质量提供了有力保证。\n.\n图3-2英备特深圳研发中心11\n图3-3英备特西安研发中心\n公司凭借先进的技术优势，完善的品质管理体系，完备的检测设施，专业的营销团队和\n及时周到的售后服务，赢得了广大客户的信赖与支持。目前已研发出了机柜式液冷一体机储\n能系统、集装箱式柔性储能系统、直流一体式充电桩系列、交流充电桩系列、超级充电集、\n直流分体式充电机系列等多款产品，多款产品在国内外具有技术优势，可广泛应用于新能源\n行业。英备特电气凭借全套软硬件支持和云服务能力，全新研发的超级光储一体化充电站设\n备已经给新能源充电行业带来了颠覆性改变。公司大力改革，不断创新，逐渐形成了自己的\n品牌优势，认真贯彻“稳健经营、全球布局、数字驱动、流程牵引”的经营理念赢得了广大\n客户的好评。\n英备特坚持以市场为导向，以客户为中心，在中国境内（北京、上海、香港）及境外\n（日本、美国、德国、马来西亚）分别设有常驻机构，已经初步建成了辐射全球主要国家和\n地区的销售网络，更好地服务本地客户，并发掘新的市场机会，在全球范围内形成了长期稳\n定、高端的客户群体。\n图3-4英备特全球服务网点图\n英备特一贯坚持以科技为先导、以质量为生命，先后通过了ISO9001:2015质量管理体\n系、ISO14001:2015环境管理体系、IECQQC080000:2017有害物质过程管理体系、IATF1216949汽车质量管理体系、知识产权管理体系认证等。公司为了配合产品销售区域的要求，\n加大力度将相关产品分别通过多种国际、国内质量与安全认证，提高产品的质量。\n图3-5英备特相关荣誉图\nISO9001:2015\n质量管理体系证书\nISO14001:2015\n环境管理体系证书\nQC080000:2017\n有害物质控制管理体系证书\nISO45001:2018\n职业健康安全管理体系证书\nIATF16949:2016\n汽车行业质量管理体系证书\nGB/T29490-2013\n知识产权管理体系证书\nAEO\n海关高级认证企业证书\n图3-6英备特相关体系证书134.工商业储能项目情况背景分析\n4.1.工商业储能项目背景\n在当前双碳目标的宏伟蓝图下，我国正加速构建以新能源为主体的新型电力系统，储能\n系统作为这一转型中的关键一环，其重要性日益凸显。通过巧妙利用储能技术在用电低谷期\n储存多余电能，并在高峰时段释放，不仅有效实现了峰谷电价差的套利机制，大幅降低了厂\n区的用电成本，还显著提升了用电效益与电能质量，为企业的可持续发展注入了强劲动力。\n这一模式还显著平抑了用户自身的用电负荷波动，有效减轻了电网的峰谷差压力，对维护电\n网稳定、促进能源高效利用具有深远的经济效益和社会效益。\n近年来，国家层面对储能产业的重视程度前所未有。自2020年中央经济工作会议明确提\n出碳达峰、碳中和目标以来，一系列政策措施密集出台，为储能项目的推广与应用提供了坚\n实的政策保障。国家不仅制定了详尽的碳达峰行动方案，鼓励有条件的地方率先达峰，还加\n快了产业结构和能源结构的调整优化步伐，推动煤炭消费逐步达峰，并大力发展风能、太阳\n能等新能源。全国用能权、碳排放权交易市场的建设步伐加快，能源消费双控制度不断完善，\n形成了多层次、全方位的碳减排政策体系。在此背景下，储能技术迎来了前所未有的发展机\n遇。随着技术的不断成熟和成本的持续下降，储能系统的经济性、可靠性和安全性显著提升，\n为其大规模商业化应用奠定了坚实基础。特别是在碳中和、碳达峰目标的指引下，未来能源\n发展将呈现三大鲜明趋势：\n在能源生产形式上，传统集中式能源生产模式正逐步向分散化、扁平化转变。随着分布\n式能源技术的广泛应用，大量自治单元之间的对等互联成为可能，电力系统变得更加灵活、\n高效；在能源生产和消费模式上，产销者一体化的趋势日益明显。用户不再仅仅是能源的消\n费者，更是生产者。通过安装分布式能源系统如屋顶光伏、风电等，每一栋建筑都能成为独\n立的能源产消者，实现能源的自给自足和余电上网，极大地促进了能源的循环利用和节约；\n在能源利用上，从高碳到低碳再到零碳的转型步伐不断加快。随着可再生能源技术的不断突\n破和成本的进一步降低，可再生能源将逐步从补充能源转变为主体能源，实现电力和燃料的\n全面零碳化。这不仅将彻底改变我国的能源结构，还将为全球应对气候变化贡献中国智慧和\n力量。储能系统在实现双碳目标、构建新型电力系统中发挥着不可替代的作用。随着技术的\n不断进步和政策的持续支持，储能产业将迎来更加广阔的发展前景，为实现能源绿色低碳转\n型、推动经济社会高质量发展作出更大贡献。14\n图4-1储能系统应用场景分析\n4.2.建设绿色工厂\n随着各级政府已陆续启动了单位GDP能耗的绩效考核体系，政府未来对于工业企业的\n能耗及节能管控标准渐趋严格，企业在绿色环保的投入及运营成本也将逐步提升，前瞻性实\n施环保节能改造将是十分必要的。对于高耗能、高排放的工商业领域而言，建设绿色工厂成\n为实现低碳转型的重要途径。绿色工厂不仅要求在生产过程中减少能源消耗和污染物排放，\n还强调资源的循环利用和生态环境的保护。结合光伏、风电等可再生能源，储能系统能够进\n一步提升绿色电力的使用比例，降低对传统化石能源的依赖，有助于提升工厂能源利用效率，\n减少碳排放，符合绿色工厂的建设标准。\n4.3.降低运营成本\n通过储能系统在用电低谷时储存电能，在高峰时释放，企业可以利用峰谷电价差实现套\n利，显著降低用电成本。随着储能技术的不断成熟和成本的进一步降低，其经济效益将更加\n显著，为企业带来长期的成本节约。储能系统可以作为备用电源，在电网停电或故障时为企\n业提供应急电力供应，减少因停电造成的生产中断和损失，稳定的电力供应有助于延长工厂\n设备的使用寿命，减少因电压波动、谐波等问题对设备的损害。\n采用合作运营的商务模式，借助于专业的能源投资渠道及运营管理优势，不仅解决了企\n业项目投资的资金压力问题，规避了能源投资及政策性补贴等中长期市场风险，也将为企业\n带来稳定的项目收益回报，降低企业运营的电力成本，有助于提升企业产品市场竞争力。\n4.4.顺应电力市场改革\n随着电力市场改革的深入，分时电价机制逐步完善，峰谷电价差逐渐增大，为储能系统\n的应用提供了更加有利的经济环境。未来电力市场将更加开放和竞争，企业可以通过参与电15力市场交易来优化用电成本。储能系统的应用将使企业在电力市场中更具竞争力。随着工商\n业领域对绿色、低碳、高效能源的需求不断增长，储能系统的市场需求也将持续增长。\n根据权威机构对各省电力市场改革及现货交易规则分析及预测，随着煤电机组逐步退役\n以及清洁能源比重增加，未来在叠加绿证成本以及发电侧峰、平、谷电价等因素后，增加自\n发电及绿色能源配置，将有助于改善企业电价成本结构及抵御电力市场化改革带来的成本波\n动。\n5.储能系统技术介绍\n5.1.第一代储能系统集成技术\n第一代储能系统集成技术即：多簇集装箱式集成+集中式PCS，如下图：\n图5-1初代储能技术示意图\n第一代储能系统存在的缺陷；\n①大量电芯串并联，存在一致性差，安装运维需要过度依赖专家；\n②电池电量失配损失大、电池系统利用率低、效率低和寿命短；\n③电池过充过放风险高，且缺乏控制手段，存在较大的安全隐患。\n5.2.第二代储能系统集成技术\n第二代储能系统技术即：单簇独立成柜+组串式PCS，如下图：\n图5-2第二代储能技术示意图16这种储能系统虽然没有了电池簇的直接并联，但簇内依然大量电芯串联，有明显的串联\n失配问题，且单级PCS架构在电网异常时有较高安全风险。\n5.3.第三代柔性储能系统集成技术\n柔性储能技术是我司新一代储能技术，创造性地提出了全新的储能系统电气拓扑，实现\n了电气拓扑级本征安全。创造性地提出了SuperBMS，将传统BMS、EMS与全电流控制系\n统高度融合，实现控制颗粒度精细到PACK的超级电池管理能力。该技术以超强的SOC均衡\n能力，解决了电池簇间和电池簇内的SOC均衡问题，解决了PACK间刚性互联和簇间刚性互\n联导致的电池容量损失问题和过冲过放导致的安全问题，使系统可放电量提升约20%，全生\n命周期成本降低15%。\n英备特第三代柔性储能系统技术，基于第二代的单簇级控制优化至电池包级控制，精确\n控制每个PACK充放电状态，实现PACK级主动故障隔离，电池簇内、簇间柔性互联，簇内、\n簇间全电流均衡，其原理如下图：\n图5-3英备特柔性储能系统技术示意图\n第三代柔性储能系统集成技术极大降低对电芯性能一致性的要求，BMU仅需均衡20节\n电芯，超出20节电芯的均衡由柔性储能电路拓扑实现。因此第三代储能系统能实现杜绝电池\n包运行在过充电或过放电状态，助力提升储能安全性；无串并联容量损失、无并联环流，实\n现100%DOD，且不提高成本与损耗；充分发挥电池容量，电池包-电池簇-电池堆容量100%\n传递；电池侧即插即用式的便捷维护性。17\n图5-4第三代柔性储能系统核心技术——全电流控制系统\n图5-5全电流控制系统电气拓扑图\n全电流控制系统作为第三代柔性储能系统的核心技术，其优势为：高安全、高效率、\n免运维。\n①电气拓扑本征安全，直流故障下无过电流；\n②精确控制每个PACK充放电状态，无过充电/放电；\n③PACK级主动故障隔离，电池簇内、簇间柔性互联，簇内、簇间全电流(140A)均衡，\n均衡能力是常规储能技术的70-1400倍；\n④零串联容损，零并联环流，400Vac直接并网，无需隔离变压器，电池、SuperBMS、\nPCS最优性能拟合，综合循环效率（含辅助损耗）大于88%；\n⑤PACK间无需配组，故障主动隔离，即插即用。186.储能系统产品类型\n6.1.机柜式储能系统\n图6-1机柜式储能系统一体机样图\n表6-1机柜式储能系统一体机产品参数\n系统技术参数\n额定电量 233kWh 海拔 ≤2000m\n额定输入电压 832Vac 工作温度 -20℃~55℃\n额定输入电压 400Vdc 环境湿度 5%~95%RH\n额定输入/输出电流 168A 热管理 液冷\n额定输入/输出电流 180A 绝缘 ≥1000Ω/V\n额定功率 125kW 耐压无击穿、无闪弧\n（3000VDC）\n防护等级 IP54 制冷量 5000W\n防腐等级 CS 辅源Max：1500W（制冷）\nMax：3000W（制热）\n尺寸（W*D*H） 1000mm*1350mm*2400mm 通讯协议 CAN/RS485/Ethernet\n质量 <2600kg 执行标准GB/T36276、GB/T34131\nGB/T34120、GB/T34133\n外观颜色 RAL9005196.2.集装箱式储能系统\n图6-2集装箱式储能系统样图\n表6-2集装箱式储能系统产品参数\n系统技术参数\n电芯类型 磷酸铁锂 通讯接口 CAN、双以太网\nPACK 314Ah/322.8V/104.5kWh 通讯协议CAN2.0、MODBUS-\nTCP、IEC61850\n簇数 12 直流接线方式 预留接线铜排M10\n额定能量 5.0159MWh 显示屏 具备\n电池管理系统 三级架构 供电方式交流侧取电400Vac，\n50kW\n热管理系统除湿空调、管路、液冷机\n组运行温度 20~35℃\nIP等级 IP54 存储湿度 RH≤95%\n重量 45t 应用海拔 ≤5000m\n尺寸(L*W*H)6058mm*2438mm*2896mm\n（20尺集装箱）噪声 70dB\n207.储能项目案例展示\n7.1.日丰企业(佛山)有限公司柔性储能项目\n图7-1日丰储能电站现场图\n2023年9月，日丰企业（佛山）有限公司9.05MW/18.1MWh储能项目正式并网运行。该\n项目投资近3000万元，年放电量预计达650万度。该储能场站由甲、乙、丙三回线上共计三\n组储能成套设备构成，它不仅是佛山市已投运容量第一的工商业储能项目，也是华南五省区\n已投运容量第三位的工商业储能项目。\n作为一家知名制造企业，日丰企业（佛山）有限公司用电量大。在国家大力倡导“双碳\n”目标、大力发展新能源产业的背景下，通过英备特投资，双方获利分成的模式，不仅\n能通过峰谷电价差获取收益和价值，也助力了日丰企业实现绿色转型发展。217.2.英备特电气科技有限公司储能项目\n图7-2英备特电气科技有限公司储能电站现场图\n英备特储能项目，装机容量为580kW/1451kWh。该项目作为英备特投资运行的首个项\n目于2022年5月投运，运行至今无故障，平均年放电量80万度，综合效率达86%。\n7.3.东莞龙鑫运动用品有限公司储能项目\n图7-3东莞龙鑫运动用品有限公司储能电站现场图\n东莞龙鑫运动用品有限公司储能项目，浙江省东莞市，储能系统装机容量\n600kW/1290kWh，整体项目于2024年1月正式投运，运行至今无故障，平均年放电量72万度，\n综合效率达86%。227.4.浙江东睦科达磁电科技有限公司储能项目\n图7-4浙江东睦科达磁电科技有限公司储能电站现场图\n浙江东睦科达磁电科技有限公司储能项目，浙江省湖州市，储能系统总装机容量\n1800kW/3870kWh，整体项目于2024年6月正式投运，系统设计按三个厂区分别低压接入一\n套600kW/1290kWh储能系统，每套储能系统适配每个厂区的用电情况进行削峰填谷收益，\n预计每年共计放电量达220万度。\n7.5.聚灿光电科技(宿迁)有限公司用户侧储能项目\n23\n图7-5聚灿光电科技(宿迁)有限公司储能电站现场图\n聚灿光电科技(宿迁)有限公司用户侧储能项目，江苏省宿迁市，储能系统总装机容量\n4.472MW/13.416MWh。本项目储能系统为用户侧储能，采取不上网模式，用地面积为543平\n方米。整体项目将于2024年10月投产，全年每天采用“2充2放”的运行策略，电价谷值和平\n值时段充电，电价峰值时段放电。本储能系统经保守测算，预计投运后年放电量约750万度。\n7.6.湖南宏旺新材料科技有限公司电化学储能项目\n图7-6湖南宏旺新材料科技有限公司储能电站位置图\n湖南宏旺新材料科技有限公司电化学储能项目，湖南省娄底市。本项目利用湖南宏旺新\n材料科技有限公司新建的铁芯厂区内未利用空地建设电化学储能电站，电站建设预计占地面\n积约1500㎡，储能系统共计接入容量为30MW/60MWh。本项目预计在2024年12月投产，整\n体项目设计生命周期为20年，预计建成后储能系统年均充放电量约2600万度。",
      "file_path": "\\uploads\\1774859130487\\顺德蚬华多媒体制品有限公司3.132MWh储能项目方案建议书20250228.pdf",
      "created_at": "2026-03-31T11:28:38.554420",
      "updated_at": "2026-03-31T11:28:38.554420"
    },
    {
      "id": "1774769457490_三水昊通EMC合同原件（扫描）.pdf",
      "filename": "三水昊通EMC合同原件（扫描）.pdf",
      "project_id": "1774769457490",
      "content": "",
      "file_path": "\\uploads\\1774769457490\\三水昊通EMC合同原件（扫描）.pdf",
      "created_at": "2026-03-31T11:55:25.973617",
      "updated_at": "2026-03-31T11:55:25.973617"
    }
  ],
  "updated_at": "2026-03-31T11:55:25.975136"
}